{"logic": 3, "analysi": 2, "program": 5, "present": 1, "system": 1, "verif": 1, "comput": 1, "incomplet": 1, "intermedi": 1, "induct": 1, "assert": 1, "provid": 1, "manual": 1, "user": 1, "termin": 2, "proven": 1, "incorrect": 2, "treat": 1, "unifi": 1, "solut": 1, "problem": 1, "paper": 2, "suggest": 1, "conduct": 1, "invari": 3, "express": 1, "actual": 1, "occur": 1, "part": 3, "devot": 1, "techniqu": 1, "automat": 2, "gener": 1, "criteria": 1, "check": 1, "simultan": 1, "correct": 2, "includ": 1, "examin": 1, "implic": 1, "approach": 1, "diagnosi": 1, "error": 1, "cacm": 1, "april": 1, "katz": 1, "manna": 1}