{"design": 2, "implement": 3, "evalu": 1, "work": 3, "set": 3, "dispatch": 2, "behavior": 3, "comput": 2, "system": 4, "larg": 1, "depend": 1, "algorithm": 1, "employ": 1, "alloc": 2, "resourc": 1, "process": 1, "compet": 1, "recent": 1, "research": 2, "time": 1, "share": 1, "page": 1, "develop": 1, "model": 2, "program": 1, "sourc": 1, "strategi": 1, "base": 2, "propos": 1, "principl": 2, "report": 2, "case": 1, "result": 1, "announc": 1, "discuss": 1, "present": 1, "data": 1, "permit": 1, "analysi": 1, "futur": 1, "direct": 1, "method": 1, "control": 1, "cacm": 1, "april": 1, "rodriguez": 1, "rosel": 1, "dupuy": 1}