{"comput": 12, "fast": 5, "fourier": 6, "transform": 9, "cooley": 1, "tukey": 1, "propos": 2, "algorithm": 3, "complex": 2, "shown": 1, "major": 2, "time": 3, "save": 1, "larg": 3, "digit": 1, "power": 1, "proport": 2, "log2": 1, "improv": 1, "method": 4, "paper": 1, "briefli": 1, "review": 1, "differ": 1, "equat": 1, "accur": 1, "need": 1, "trigonometr": 1, "function": 1, "valu": 1, "problem": 1, "system": 1, "virtual": 1, "memori": 1, "consid": 1, "solut": 1, "size": 2, "word": 1, "core": 2, "storag": 2, "exce": 1, "factor": 1, "maximum": 1, "radix": 2, "fix": 2, "alloc": 1, "amount": 1, "mix": 1, "scale": 1, "plan": 1, "point": 1, "arithmet": 1, "cacm": 1, "octob": 1, "singleton": 1}