{"a": 2, "free": 3, "storag": 5, "packag": 3, "fundament": 1, "underli": 1, "problem": 2, "sophist": 1, "softwar": 1, "system": 2, "involv": 1, "elabor": 1, "chang": 1, "data": 1, "structur": 1, "dynam": 1, "alloc": 1, "flexibl": 1, "model": 1, "compil": 1, "block": 2, "obtain": 1, "reus": 1, "total": 1, "space": 2, "partit": 1, "hierarchi": 1, "zone": 2, "characterist": 1, "size": 2, "special": 1, "provis": 1, "allow": 2, "effici": 1, "handl": 1, "select": 1, "control": 2, "shatter": 1, "garbag": 1, "collect": 1, "share": 1, "physic": 1, "routin": 1, "perform": 1, "high": 1, "level": 1, "function": 1, "access": 1, "fine": 1, "intern": 1, "detail": 1, "cacm": 1, "august": 1, "ross": 1}