{"break": 3, "substitut": 4, "cipher": 4, "relax": 1, "algorithm": 1, "code": 3, "letter": 5, "alphabet": 1, "fix": 1, "word": 1, "divis": 1, "chang": 1, "paper": 1, "problem": 2, "repres": 2, "probabilist": 1, "label": 1, "assign": 1, "probabl": 3, "plain": 1, "text": 1, "updat": 2, "parallel": 1, "joint": 1, "iter": 1, "scheme": 1, "result": 1, "improv": 1, "estim": 1, "final": 1, "lead": 1, "method": 1, "appli": 1, "success": 1, "exampl": 1, "cacm": 1, "novemb": 1, "peleg": 1, "rosenfeld": 1}