{"manag": 1, "scienc": 1, "view": 1, "nonlinear": 3, "program": 4, "histori": 1, "integ": 1, "continu": 1, "present": 1, "obstacl": 1, "practic": 1, "mathemat": 1, "techniqu": 2, "forecast": 1, "contribut": 2, "actual": 1, "made": 1, "year": 1, "like": 2, "consolid": 1, "theoret": 1, "breakthrough": 1, "document": 1, "standard": 1, "test": 1, "problem": 2, "construct": 1, "user": 1, "orient": 1, "softwar": 1, "comparison": 1, "known": 1, "algorithm": 1, "demonstr": 1, "specif": 1, "cacm": 1, "juli": 1, "shanno": 1, "weil": 1}