{"occurr": 1, "cycl": 6, "phenomena": 2, "aris": 1, "class": 2, "linear": 3, "program": 3, "model": 2, "investig": 1, "averag": 1, "queue": 2, "size": 1, "result": 2, "formul": 1, "problem": 3, "ill": 1, "condit": 1, "case": 2, "attempt": 2, "solv": 2, "ibm": 1, "mp": 2, "packag": 1, "instanc": 1, "encount": 1, "small": 1, "perturb": 2, "input": 1, "data": 1, "fact": 1, "observ": 1, "suggest": 1, "primari": 1, "reason": 1, "known": 1, "occur": 1, "frequent": 1, "round": 1, "error": 1, "comput": 1, "suffici": 1, "prevent": 2, "indefinit": 1, "maxim": 1, "minim": 1, "object": 1, "function": 1, "subject": 1, "constrain": 1, "set": 1, "give": 1, "indic": 1, "infeas": 1, "cacm": 1, "februari": 1, "kotiah": 1, "steinberg": 1}